doopl-12.10.0.26.data/purelib/doopl/__init__.py
doopl-12.10.0.26.data/purelib/doopl/factory.py
doopl-12.10.0.26.data/purelib/doopl/opl.py
doopl-12.10.0.26.data/purelib/doopl/version.py
doopl-12.10.0.26.data/purelib/doopl/internal/__init__.py
doopl-12.10.0.26.data/purelib/doopl/internal/opl12100/__init__.py
doopl-12.10.0.26.data/purelib/doopl/internal/opl12100/_opl.so
doopl-12.10.0.26.data/purelib/doopl/internal/opl12100/opl.py
doopl-12.10.0.26.data/purelib/doopl/internal/opl1280/__init__.py
doopl-12.10.0.26.data/purelib/doopl/internal/opl1280/_opl.so
doopl-12.10.0.26.data/purelib/doopl/internal/opl1280/opl.py
doopl-12.10.0.26.data/purelib/doopl/internal/opl1290/__init__.py
doopl-12.10.0.26.data/purelib/doopl/internal/opl1290/_opl.so
doopl-12.10.0.26.data/purelib/doopl/internal/opl1290/opl.py
doopl-12.10.0.26.dist-info/License.txt
doopl-12.10.0.26.dist-info/METADATA
doopl-12.10.0.26.dist-info/WHEEL
doopl-12.10.0.26.dist-info/RECORD
