Metadata-Version: 2.1
Name: doopl
Version: 12.10.0.26
Summary: A Python interface to OPL.
Home-page: https://www.ibm.com/analytics/data-science/prescriptive-analytics/cplex-optimizer/
Author: IBM
Author-email: UNKNOWN
License: UNKNOWN
Platform: UNKNOWN
